pandas_tab/__init__.py
pandas_tab/__main__.py
pandas_tab/cli.py
pandas_tab/core.py
pandas_tab/scripts/jupyter_init.py.jinja
pandas_tab-0.1.3.dist-info/LICENSE
pandas_tab-0.1.3.dist-info/METADATA
pandas_tab-0.1.3.dist-info/WHEEL
pandas_tab-0.1.3.dist-info/entry_points.txt
pandas_tab-0.1.3.dist-info/top_level.txt
pandas_tab-0.1.3.dist-info/RECORD
