Metadata-Version: 2.1
Name: pandas-tab
Version: 0.1.3
Summary: Data exploration done quick.
Home-page: https://github.com/ryxcommar/pandas_tab
Author: ryxcommar
Author-email: ryxcommar@gmail.com
License: MIT
Platform: UNKNOWN
Classifier: Development Status :: 1 - Planning
Classifier: Environment :: Plugins
Classifier: Intended Audience :: Science/Research
Classifier: License :: OSI Approved :: BSD License
Classifier: Operating System :: OS Independent
Classifier: Topic :: Scientific/Engineering
Classifier: Programming Language :: Python :: 3
Classifier: Programming Language :: Python :: 3.7
Classifier: Programming Language :: Python :: 3.8
Classifier: Programming Language :: Python :: 3.9
Classifier: Programming Language :: Python :: 3.10
Requires-Python: >=3.6.1
Requires-Dist: pandas (>=0.23.0)
Requires-Dist: click
Provides-Extra: full
Requires-Dist: jinja2 ; extra == 'full'
Requires-Dist: IPython ; extra == 'full'
